google_search_scraper/__init__.py
google_search_scraper/cli.py
google_search_scraper/exceptions.py
google_search_scraper/scraper.py
google_search_aj-1.0.6.dist-info/METADATA
google_search_aj-1.0.6.dist-info/WHEEL
google_search_aj-1.0.6.dist-info/entry_points.txt
google_search_aj-1.0.6.dist-info/top_level.txt
google_search_aj-1.0.6.dist-info/RECORD
