Metadata-Version: 2.4
Name: google-search-aj
Version: 1.0.6
Summary: Fast, lightweight Google search scraper with stealth mode
Home-page: https://github.com/Aaditya17032002/google-search
Author: Aditya Jangam
Author-email: Aditya Jangam <adityajangam25@gmail.com>
License-Expression: MIT
Project-URL: Homepage, https://github.com/Aaditya17032002/google-search
Project-URL: Documentation, https://github.com/Aaditya17032002/google-search#readme
Project-URL: Repository, https://github.com/Aaditya17032002/google-search
Project-URL: Bug Tracker, https://github.com/Aaditya17032002/google-search/issues
Keywords: google,search,scraper,web-scraping,playwright,automation
Classifier: Development Status :: 4 - Beta
Classifier: Intended Audience :: Developers
Classifier: Topic :: Software Development :: Libraries :: Python Modules
Classifier: Topic :: Internet :: WWW/HTTP :: Indexing/Search
Classifier: Programming Language :: Python :: 3
Classifier: Programming Language :: Python :: 3.8
Classifier: Programming Language :: Python :: 3.9
Classifier: Programming Language :: Python :: 3.10
Classifier: Programming Language :: Python :: 3.11
Classifier: Programming Language :: Python :: 3.12
Requires-Python: >=3.8
Requires-Dist: playwright>=1.40.0
Requires-Dist: beautifulsoup4>=4.12.0
Provides-Extra: dev
Requires-Dist: pytest>=7.0.0; extra == "dev"
Requires-Dist: pytest-cov>=4.0.0; extra == "dev"
Requires-Dist: black>=23.0.0; extra == "dev"
Requires-Dist: flake8>=6.0.0; extra == "dev"
Requires-Dist: mypy>=1.0.0; extra == "dev"
Dynamic: author
Dynamic: home-page
Dynamic: requires-python
